bytes32/__init__.py
bytes32/alignment.py
bytes32/compliance.py
bytes32/utils.py
bytes32/validity.py
bytes32/version.py
bytes32/winnability/__init__.py
bytes32/winnability/language_agent.py
bytes32-1.1.1.dist-info/LICENSE
bytes32-1.1.1.dist-info/METADATA
bytes32-1.1.1.dist-info/WHEEL
bytes32-1.1.1.dist-info/top_level.txt
bytes32-1.1.1.dist-info/RECORD
