Metadata-Version: 2.1
Name: bytes32
Version: 1.1.1
Summary: Byte-sized text games for code generation tasks on virtual environments.
Home-page: https://github.com/cognitiveailab/BYTESIZED32
Author: Ruoyao Wang, Graham Todd, Eric Yuan, Ziang Xiao, Marc-Alexandre Côté, Peter Jansen
Classifier: Programming Language :: Python :: 3
Classifier: License :: OSI Approved :: Apache Software License
Classifier: Operating System :: POSIX :: Linux
Classifier: Operating System :: MacOS :: MacOS X
License-File: LICENSE
Requires-Dist: openai >=1.0.0
Requires-Dist: tiktoken
Requires-Dist: pandas
Requires-Dist: tqdm
Requires-Dist: plotly
Requires-Dist: tenacity
